{
   "mixins": "stonehearth:mixins:item_properties",
   "type": "entity",
   "components": {
      "render_info": {
         "color_map": "stonehearth_ace:color_map:ace",
         "material_maps": [
            "/stonehearth/data/materials/material_maps/glass_material_map.json"
         ],
         "scale": 0.09
      },
      "model_variants": {
         "default": {
            "models": [
               "file(comb.qb)",
               "file(honey_1.qb)",
               "file(honey_2.qb)"
            ]
         }
      },
      "mob": {
         "model_origin": { "x": 0, "y": 0, "z": 0.05 }
      },
      "stonehearth:stacks": {
         "max_stacks": 2
      }
   },
   "entity_data": {
      "stonehearth:food_container": {
         "effect": "fiddle",
         "food": "stonehearth_ace:food:honey:honey_wild_serving",
         "stacks_per_serving": 2
      },
      "stonehearth:net_worth": {
         "value_in_gold": 9,
         "rarity": "common",
         "shop_info": {
            "buyable": false,
            "sellable": true
         }
      },
      "stonehearth:catalog": {
         "display_name": "i18n(stonehearth_ace:entities.food.honey.honey_wild.display_name)",
         "description": "i18n(stonehearth_ace:entities.food.honey.honey_wild.description)",
         "icon": "file(honey_wild.png)",
         "is_item": true,
         "category": "cooking_ingredient",
         "material_tags": [
            "stockpile_cooking_ingredient",
            "cooking_ingredient",
            "food",
            "food_container",
            "honey_wild",
            "honey",
            "sweetener",
            "raw_food",
            "other_ingredient",
            "breakfast_time"
         ]
      },
      "stonehearth:appeal": {
         "appeal": 3
      }
   }
}
