{
   "mixins": "stonehearth:mixins:placed_object",
   "components": {
      "model_variants": {
         "default": {
            "models": [
               "file(mega_turnip.qb)"
            ]
         }
      },
      "render_info": {
         "scale": 0.1
      },
      "mob": {
         "model_origin": { "x": 0, "y": 0, "z": 0 },
         "region_origin": { "x": 0.5, "y": 0, "z": 0.5 }
      }
   },
   "entity_data": {
      "stonehearth:catalog": {
         "display_name": "i18n(stonehearth_ace:entities.decoration.megacrop.mega_turnip.display_name)",
         "description": "i18n(stonehearth_ace:entities.decoration.megacrop.mega_turnip.description)",
         "icon": "file(mega_turnip.png)",
         "category": "decoration",
         "material_tags": [
            "decoration",
            "megacrop",
            "turnip",
            "stockpile_decoration",
            "stockpile_raw_foods"
         ]
      }
   }
}
