{
   "type": "recipe",
   "effort": 40,
   "work_units": 5,
   "recipe_name": "i18n(stonehearth_ace:jobs.blacksmith.recipes.mason_chisel_iron_recipe.recipe_name)",
   "description": "i18n(stonehearth_ace:jobs.blacksmith.recipes.mason_chisel_iron_recipe.description)",
   "flavor": "i18n(stonehearth_ace:jobs.blacksmith.recipes.mason_chisel_iron_recipe.flavor)",
   "portrait": "/stonehearth_ace/entities/tools/mason_chisel_iron/mason_chisel_iron.png",
   "workshop": "stonehearth:blacksmith:workbench",
   "level_requirement": 3,
   "ingredients": [
      {
         "uri": "stonehearth:refined:iron_ingot",
         "count": 1
      },
		{
         "material": "wood resource",
         "count": 1
      }
   ],
   "produces": [
      {
         "item": "stonehearth_ace:tools:mason_chisel_iron"
      }
   ]
}
