{
   "type": "trait",
   "display_name": "i18n(stonehearth_ace:data.traits.vegetable_love_trait.display_name)",
   "description": "i18n(stonehearth_ace:data.traits.vegetable_love_trait.description)",
   "icon": "file(vegetable_love_trait.png)",
   "script_controller": "stonehearth:trait_scripts:food_preference",
   "data": {
      "food_preferences": "vegetarian",
      "preference_effect": "stonehearth_ace:buffs:lovely_meal",
      "lovely_thought": "stonehearth:thoughts:eating:vegetable_lover_ate_vegetable"
   }
}
