{
   "mixins": "/stonehearth_ace/scenarios/static/static_objects/static_objects.json",
   "name": "forest_arctic",
   "mixintypes": {
      "habitat_types": "override"
   },
   "habitat_types": [
      "forest"
   ],
   "size": {
      "width": 48,
      "length": 48
   },
   "biomes": [
      "stonehearth:biome:arctic"
   ],
   "data": {
      "entity_type": [
         "stonehearth_ace:trees:pine:trunk",
         "stonehearth_ace:trees:pine:trunk",
         "stonehearth_ace:trees:juniper:trunk",
         "stonehearth_ace:trees:juniper:trunk",
         "stonehearth_ace:trees:old_wood:trunk",
         "stonehearth_ace:trees:old_wood:stump",
         "stonehearth_ace:boulder:forest:small",
         "stonehearth_ace:boulder:forest:medium_1",
         "stonehearth_ace:boulder:forest:medium_2",
         "stonehearth_ace:boulder:forest:medium_3",
         "stonehearth_ace:boulder:forest:large_1",
         "stonehearth_ace:boulder:forest:large_2",
         "stonehearth_ace:fungi:parasol",
         "stonehearth_ace:fungi:parasol",
         "stonehearth_ace:fungi:parasol:spreading",
         "stonehearth_ace:fungi:parasol:developing",
         "stonehearth_ace:fungi:sweet_tooth",
         "stonehearth_ace:fungi:sweet_tooth",
         "stonehearth_ace:fungi:sweet_tooth:spreading",
         "stonehearth_ace:fungi:sweet_tooth:developing",
         "stonehearth_ace:fungi:parasol:spreading",
         "stonehearth_ace:fungi:parasol:developing",
         "stonehearth_ace:fungi:sweet_tooth:spreading",
         "stonehearth_ace:fungi:sweet_tooth:developing"
      ],
      "quantity": {
         "min": 2,
         "max": 10
      }
   }
}
