{
   "effort": 12,
   "level_requirement": 2,
   "recipe_name": "i18n(stonehearth_ace:jobs.mason.recipes.cobblestone_fence_end_recipe.recipe_name)",
   "proficiency_gain": 0.5,
   "mixintypes": {
      "ingredients": "override",
      "produces": "override"
   },
   "ingredients": [
      {
         "material": "stone resource",
         "count": 2
      }
   ],
   "produces": [
      {
         "item": "stonehearth:construction:cobblestone_fence:end"
      },
      {
         "item": "stonehearth:construction:cobblestone_fence:end"
      },
      {
         "item": "stonehearth:construction:cobblestone_fence:end"
      },
      {
         "item": "stonehearth:construction:cobblestone_fence:end"
      }
   ]
}
