{
   "mixins": "stonehearth:mixins:item_properties",
   "type": "entity",
   "components": {
      "model_variants": {
         "default": {
            "models": [
               "file(cream.qb)"
            ]
         }
      },
      "mob": {
         "model_origin": { "x": 0, "y": 0, "z": 0 }
      }
   },
   "entity_data": {
      "stonehearth:net_worth": {
         "value_in_gold": 7,
         "rarity": "uncommon",
         "shop_info": {
            "buyable": true,
            "sellable": true,
            "shopkeeper_level": 2,
            "shopkeeper_type": "caravan"
         }
      },
      "stonehearth:catalog": {
         "display_name": "i18n(stonehearth_ace:entities.food.dairy.cream.display_name)",
         "description": "i18n(stonehearth_ace:entities.food.dairy.cream.description)",
         "icon": "file(cream.png)",
         "is_item": true,
         "category": "food",
         "material_tags": [
            "cream",
            "standard",
            "dairy",
            "cooking_ingredient",
            "other_fluid",
            "stockpile_cooking_ingredient",
            "animal_ingredient"
         ]
      },
      "stonehearth:appeal": {
         "appeal": 2
      },
      "stonehearth:item_quality": {
         "variable_quality": true
      }
   }
}
